gratopy/__init__.py
gratopy/fanbeam.cl
gratopy/gratopy.py
gratopy/phantom.py
gratopy/radon.cl
gratopy/total_variation.cl
gratopy/utilities.cl
gratopy-0.1.0.dist-info/LICENSE
gratopy-0.1.0.dist-info/METADATA
gratopy-0.1.0.dist-info/WHEEL
gratopy-0.1.0.dist-info/top_level.txt
gratopy-0.1.0.dist-info/RECORD
