Metadata-Version: 2.1
Name: gratopy
Version: 0.1.0
Summary: Gratopy - Graz accelerated tomographic projections for Python
Home-page: https://github.com/kbredies/gratopy
Author: Kristian Bredies, Richard Huber
Author-email: kristian.bredies@uni-graz.at
License: GPLv3
Project-URL: Documentation, https://gratopy.readthedocs.io/
Keywords: Radon transform,fanbeam transform,pixel-driven projection methods,computed tomography,image reconstruction,pyopencl
Platform: UNKNOWN
Classifier: Environment :: Console
Classifier: Environment :: GPU
Classifier: Development Status :: 4 - Beta
Classifier: Intended Audience :: Developers
Classifier: Intended Audience :: Other Audience
Classifier: Intended Audience :: Science/Research
Classifier: License :: OSI Approved :: GNU General Public License v3 (GPLv3)
Classifier: Programming Language :: Python :: 3
Classifier: Programming Language :: C
Classifier: Topic :: Scientific/Engineering
Classifier: Topic :: Scientific/Engineering :: Mathematics
Classifier: Topic :: Scientific/Engineering :: Physics
Classifier: Topic :: Scientific/Engineering :: Image Processing
Requires-Python: >=3.6
License-File: LICENSE
Requires-Dist: matplotlib (>=3.2.0)
Requires-Dist: numpy (>=1.17.0)
Requires-Dist: pyopencl (>=2019.1)
Requires-Dist: scipy (>=1.3.0)
Requires-Dist: Pillow (>=6.0.0)
Requires-Dist: mako (>=1.1.0)
